{
  "tags": [
    {
      "teams": [
        {
          "cElapsed": 2707680,
          "old": false,
          "d24": 128771,
          "started": true,
          "finished": true,
          "elapsed": 2707680,
          "cElapsedFormatted": "31d 8h 8m 0s",
          "rankR": 1,
          "rankS": 1,
          "tcf": "1.000",
          "dtf": 0,
          "id": 14,
          "finishAt": 1768419240,
          "elapsedFormatted": "31d 8h 8m 0s",
          "dmg": 4961713,
          "status": "RACING"
        },
        {
          "cElapsed": 2802060,
          "old": false,
          "d24": 154195,
          "started": true,
          "finished": true,
          "elapsed": 2802060,
          "cElapsedFormatted": "32d 10h 21m 0s",
          "rankR": 2,
          "rankS": 2,
          "tcf": "1.000",
          "dtf": 0,
          "id": 16,
          "finishAt": 1768513860,
          "elapsedFormatted": "32d 10h 21m 0s",
          "dmg": 4970999,
          "status": "RACING"
        },
        {
          "cElapsed": 2945460,
          "old": false,
          "d24": 131402,
          "started": true,
          "finished": true,
          "elapsed": 2945460,
          "cElapsedFormatted": "34d 2h 11m 0s",
          "rankR": 3,
          "rankS": 3,
          "tcf": "1.000",
          "dtf": 0,
          "id": 15,
          "finishAt": 1768657140,
          "elapsedFormatted": "34d 2h 11m 0s",
          "dmg": 4966715,
          "status": "RACING"
        },
        {
          "cElapsed": 3033900,
          "old": false,
          "d24": 107116,
          "started": true,
          "finished": true,
          "elapsed": 3033900,
          "cElapsedFormatted": "35d 2h 45m 0s",
          "rankR": 4,
          "rankS": 4,
          "tcf": "1.000",
          "dtf": 0,
          "id": 2,
          "finishAt": 1768744020,
          "elapsedFormatted": "35d 2h 45m 0s",
          "dmg": 4933692,
          "status": "RACING"
        },
        {
          "cElapsed": 3065400,
          "old": false,
          "d24": 168055,
          "started": true,
          "finished": true,
          "elapsed": 3065400,
          "cElapsedFormatted": "35d 11h 30m 0s",
          "rankR": 5,
          "rankS": 5,
          "tcf": "1.000",
          "dtf": 0,
          "id": 19,
          "finishAt": 1768777560,
          "elapsedFormatted": "35d 11h 30m 0s",
          "dmg": 5003931,
          "status": "RACING"
        },
        {
          "cElapsed": 3153480,
          "old": false,
          "d24": 157514,
          "started": true,
          "finished": true,
          "elapsed": 3153480,
          "cElapsedFormatted": "36d 11h 58m 0s",
          "rankR": 6,
          "rankS": 6,
          "tcf": "1.000",
          "dtf": 0,
          "id": 27,
          "finishAt": 1768866600,
          "elapsedFormatted": "36d 11h 58m 0s",
          "dmg": 4984428,
          "status": "RACING"
        },
        {
          "cElapsed": 3193380,
          "old": false,
          "d24": 148902,
          "started": true,
          "finished": true,
          "elapsed": 3193380,
          "cElapsedFormatted": "36d 23h 3m 0s",
          "rankR": 7,
          "rankS": 7,
          "tcf": "1.000",
          "dtf": 0,
          "id": 13,
          "finishAt": 1768904820,
          "elapsedFormatted": "36d 23h 3m 0s",
          "dmg": 4975343,
          "status": "RACING"
        },
        {
          "cElapsed": 3201180,
          "old": false,
          "d24": 140941,
          "started": true,
          "finished": true,
          "elapsed": 3201180,
          "cElapsedFormatted": "37d 1h 13m 0s",
          "rankR": 8,
          "rankS": 8,
          "tcf": "1.000",
          "dtf": 0,
          "id": 23,
          "finishAt": 1768913820,
          "elapsedFormatted": "37d 1h 13m 0s",
          "dmg": 4890226,
          "status": "RACING"
        },
        {
          "cElapsed": 3297600,
          "old": false,
          "d24": 152344,
          "started": true,
          "finished": true,
          "elapsed": 3297600,
          "cElapsedFormatted": "38d 4h 0m 0s",
          "rankR": 9,
          "rankS": 9,
          "tcf": "1.000",
          "dtf": 0,
          "id": 7,
          "finishAt": 1769008320,
          "elapsedFormatted": "38d 4h 0m 0s",
          "dmg": 4987043,
          "status": "RACING"
        },
        {
          "eElapsedR": 3316860,
          "eElapsedS": 3317362,
          "old": false,
          "eElapsedRFormatted": "38d 9h 21m 0s",
          "d24": 142693,
          "started": true,
          "finished": false,
          "eFinishS": 1769028442,
          "eFinishR": 1769027940,
          "ceElapsedRFormatted": "38d 9h 21m 0s",
          "eElapsedSFormatted": "38d 9h 29m 22s",
          "rankR": 10,
          "rankS": 10,
          "vmgS": 5.149450767100888,
          "cElapsedS": 3317362,
          "vmgR": 5.948656187188626,
          "tcf": "1.000",
          "cElapsedR": 3316860,
          "dtf": 5353,
          "ceElapsedSFormatted": "38d 9h 29m 22s",
          "id": 10,
          "dmg": 4983163,
          "status": "RACING"
        },
        {
          "eElapsedR": 3327475,
          "eElapsedS": 3334151,
          "old": false,
          "eElapsedRFormatted": "38d 12h 17m 55s",
          "d24": 163977,
          "started": true,
          "finished": false,
          "eFinishS": 1769047031,
          "eFinishR": 1769040355,
          "ceElapsedRFormatted": "38d 12h 17m 55s",
          "eElapsedSFormatted": "38d 14h 9m 11s",
          "rankR": 11,
          "rankS": 11,
          "vmgS": 5.123521558518877,
          "cElapsedS": 3334151,
          "vmgR": 7.308248235976361,
          "tcf": "1.000",
          "cElapsedR": 3327475,
          "dtf": 31782,
          "ceElapsedSFormatted": "38d 14h 9m 11s",
          "id": 25,
          "dmg": 5030946,
          "status": "RACING"
        },
        {
          "eElapsedR": 3362153,
          "eElapsedS": 3372818,
          "old": false,
          "eElapsedRFormatted": "38d 21h 55m 53s",
          "d24": 140011,
          "started": true,
          "finished": false,
          "eFinishS": 1769084738,
          "eFinishR": 1769074073,
          "ceElapsedRFormatted": "38d 21h 55m 53s",
          "eElapsedSFormatted": "39d 0h 53m 38s",
          "rankR": 12,
          "rankS": 12,
          "vmgS": 5.064783813655568,
          "cElapsedS": 3372818,
          "vmgR": 6.102153211971003,
          "tcf": "1.000",
          "cElapsedR": 3362153,
          "dtf": 88264,
          "ceElapsedSFormatted": "39d 0h 53m 38s",
          "id": 17,
          "dmg": 4916730,
          "status": "RACING"
        },
        {
          "eElapsedR": 3414797,
          "eElapsedS": 3447793,
          "old": false,
          "eElapsedRFormatted": "39d 12h 33m 17s",
          "d24": 144177,
          "started": true,
          "finished": false,
          "eFinishS": 1769161633,
          "eFinishR": 1769128637,
          "ceElapsedRFormatted": "39d 12h 33m 17s",
          "eElapsedSFormatted": "39d 21h 43m 13s",
          "rankR": 13,
          "rankS": 13,
          "vmgS": 4.954646365753952,
          "cElapsedS": 3447793,
          "vmgR": 6.437748252972931,
          "tcf": "1.000",
          "cElapsedR": 3414797,
          "dtf": 197123,
          "ceElapsedSFormatted": "39d 21h 43m 13s",
          "id": 33,
          "dmg": 4757377,
          "status": "RACING"
        },
        {
          "eElapsedR": 3451296,
          "eElapsedS": 3483117,
          "old": false,
          "eElapsedRFormatted": "39d 22h 41m 36s",
          "d24": 132433,
          "started": true,
          "finished": false,
          "eFinishS": 1769197077,
          "eFinishR": 1769165256,
          "ceElapsedRFormatted": "39d 22h 41m 36s",
          "eElapsedSFormatted": "40d 7h 31m 57s",
          "rankR": 14,
          "rankS": 14,
          "vmgS": 4.904398613434057,
          "cElapsedS": 3483117,
          "vmgR": 5.967149759177435,
          "tcf": "1.000",
          "cElapsedR": 3451296,
          "dtf": 243410,
          "ceElapsedSFormatted": "40d 7h 31m 57s",
          "id": 34,
          "dmg": 4706738,
          "status": "RACING"
        },
        {
          "eElapsedR": 3442813,
          "eElapsedS": 3489919,
          "old": false,
          "eElapsedRFormatted": "39d 20h 20m 13s",
          "d24": 138927,
          "started": true,
          "finished": false,
          "eFinishS": 1769200399,
          "eFinishR": 1769153293,
          "ceElapsedRFormatted": "39d 20h 20m 13s",
          "eElapsedSFormatted": "40d 9h 25m 19s",
          "rankR": 15,
          "rankS": 15,
          "vmgS": 4.894840473735954,
          "cElapsedS": 3489919,
          "vmgR": 6.6041586622066575,
          "tcf": "1.000",
          "cElapsedR": 3442813,
          "dtf": 247460,
          "ceElapsedSFormatted": "40d 9h 25m 19s",
          "id": 5,
          "dmg": 4776675,
          "status": "RACING"
        },
        {
          "eElapsedR": 3526940,
          "eElapsedS": 3597361,
          "old": false,
          "eElapsedRFormatted": "40d 19h 42m 20s",
          "d24": 151585,
          "started": true,
          "finished": false,
          "eFinishS": 1769309761,
          "eFinishR": 1769239340,
          "ceElapsedRFormatted": "40d 19h 42m 20s",
          "eElapsedSFormatted": "41d 15h 16m 1s",
          "rankR": 16,
          "rankS": 16,
          "vmgS": 4.748645860990097,
          "cElapsedS": 3597361,
          "vmgR": 6.214537886290416,
          "tcf": "1.000",
          "cElapsedR": 3526940,
          "dtf": 393800,
          "ceElapsedSFormatted": "41d 15h 16m 1s",
          "id": 21,
          "dmg": 4619900,
          "status": "RACING"
        },
        {
          "eElapsedR": 3506635,
          "eElapsedS": 3598089,
          "old": false,
          "eElapsedRFormatted": "40d 14h 3m 55s",
          "d24": 160142,
          "started": true,
          "finished": false,
          "eFinishS": 1769312769,
          "eFinishR": 1769221315,
          "ceElapsedRFormatted": "40d 14h 3m 55s",
          "eElapsedSFormatted": "41d 15h 28m 9s",
          "rankR": 17,
          "rankS": 17,
          "vmgS": 4.747685295103189,
          "cElapsedS": 3598089,
          "vmgR": 6.814209847289504,
          "tcf": "1.000",
          "cElapsedR": 3506635,
          "dtf": 397703,
          "ceElapsedSFormatted": "41d 15h 28m 9s",
          "id": 40,
          "dmg": 4558855,
          "status": "RACING"
        },
        {
          "eElapsedR": 3631008,
          "eElapsedS": 3717527,
          "old": false,
          "eElapsedRFormatted": "42d 0h 36m 48s",
          "d24": 135216,
          "started": true,
          "finished": false,
          "eFinishS": 1769430047,
          "eFinishR": 1769343528,
          "ceElapsedRFormatted": "42d 0h 36m 48s",
          "eElapsedSFormatted": "43d 0h 38m 47s",
          "rankR": 18,
          "rankS": 18,
          "vmgS": 4.595150129916895,
          "cElapsedS": 3717527,
          "vmgR": 5.791479037351371,
          "tcf": "1.000",
          "cElapsedR": 3631008,
          "dtf": 534622,
          "ceElapsedSFormatted": "43d 0h 38m 47s",
          "id": 22,
          "dmg": 4543260,
          "status": "RACING"
        },
        {
          "eElapsedR": 3610724,
          "eElapsedS": 3717665,
          "old": false,
          "eElapsedRFormatted": "41d 18h 58m 44s",
          "d24": 143682,
          "started": true,
          "finished": false,
          "eFinishS": 1769431385,
          "eFinishR": 1769324444,
          "ceElapsedRFormatted": "41d 18h 58m 44s",
          "eElapsedSFormatted": "43d 0h 41m 5s",
          "rankR": 19,
          "rankS": 19,
          "vmgS": 4.59497961354953,
          "cElapsedS": 3717665,
          "vmgR": 6.163729589426269,
          "tcf": "1.000",
          "cElapsedR": 3610724,
          "dtf": 536311,
          "ceElapsedSFormatted": "43d 0h 41m 5s",
          "id": 32,
          "dmg": 4387043,
          "status": "RACING"
        },
        {
          "eElapsedR": 3599379,
          "eElapsedS": 3721994,
          "old": false,
          "eElapsedRFormatted": "41d 15h 49m 39s",
          "d24": 154072,
          "started": true,
          "finished": false,
          "eFinishS": 1769435594,
          "eFinishR": 1769312979,
          "ceElapsedRFormatted": "41d 15h 49m 39s",
          "eElapsedSFormatted": "43d 1h 53m 14s",
          "rankR": 20,
          "rankS": 20,
          "vmgS": 4.5896352676235885,
          "cElapsedS": 3721994,
          "vmgR": 6.454458333249591,
          "tcf": "1.000",
          "cElapsedR": 3599379,
          "dtf": 541053,
          "ceElapsedSFormatted": "43d 1h 53m 14s",
          "id": 31,
          "dmg": 4415360,
          "status": "RACING"
        },
        {
          "eElapsedR": 3674435,
          "eElapsedS": 3780013,
          "old": false,
          "eElapsedRFormatted": "42d 12h 40m 35s",
          "d24": 141285,
          "started": true,
          "finished": false,
          "eFinishS": 1769493253,
          "eFinishR": 1769387675,
          "ceElapsedRFormatted": "42d 12h 40m 35s",
          "eElapsedSFormatted": "43d 18h 0m 13s",
          "rankR": 21,
          "rankS": 21,
          "vmgS": 4.519189013600028,
          "cElapsedS": 3780013,
          "vmgR": 5.786640141411118,
          "tcf": "1.000",
          "cElapsedR": 3674435,
          "dtf": 605099,
          "ceElapsedSFormatted": "43d 18h 0m 13s",
          "id": 28,
          "dmg": 4390195,
          "status": "RACING"
        },
        {
          "eElapsedR": 3648651,
          "eElapsedS": 3781209,
          "old": false,
          "eElapsedRFormatted": "42d 5h 30m 51s",
          "d24": 146040,
          "started": true,
          "finished": false,
          "eFinishS": 1769493489,
          "eFinishR": 1769360931,
          "ceElapsedRFormatted": "42d 5h 30m 51s",
          "eElapsedSFormatted": "43d 18h 20m 9s",
          "rankR": 22,
          "rankS": 22,
          "vmgS": 4.517760148038581,
          "cElapsedS": 3781209,
          "vmgR": 6.230140755585879,
          "tcf": "1.000",
          "cElapsedR": 3648651,
          "dtf": 605234,
          "ceElapsedSFormatted": "43d 18h 20m 9s",
          "id": 20,
          "dmg": 4481049,
          "status": "RACING"
        },
        {
          "eElapsedR": 3651117,
          "eElapsedS": 3781094,
          "old": false,
          "eElapsedRFormatted": "42d 6h 11m 57s",
          "d24": 146340,
          "started": true,
          "finished": false,
          "eFinishS": 1769495534,
          "eFinishR": 1769365557,
          "ceElapsedRFormatted": "42d 6h 11m 57s",
          "eElapsedSFormatted": "43d 18h 18m 14s",
          "rankR": 23,
          "rankS": 23,
          "vmgS": 4.517897032286437,
          "cElapsedS": 3781094,
          "vmgR": 6.1750718134451095,
          "tcf": "1.000",
          "cElapsedR": 3651117,
          "dtf": 607820,
          "ceElapsedSFormatted": "43d 18h 18m 14s",
          "id": 38,
          "dmg": 4336698,
          "status": "RACING"
        },
        {
          "eElapsedR": 3637102,
          "eElapsedS": 3807439,
          "old": false,
          "eElapsedRFormatted": "42d 2h 18m 22s",
          "d24": 158411,
          "started": true,
          "finished": false,
          "eFinishS": 1769522479,
          "eFinishR": 1769352142,
          "ceElapsedRFormatted": "42d 2h 18m 22s",
          "eElapsedSFormatted": "44d 1h 37m 19s",
          "rankR": 24,
          "rankS": 24,
          "vmgS": 4.486635960121709,
          "cElapsedS": 3807439,
          "vmgR": 6.728233220476782,
          "tcf": "1.000",
          "cElapsedR": 3637102,
          "dtf": 637195,
          "ceElapsedSFormatted": "44d 1h 37m 19s",
          "id": 43,
          "dmg": 4512241,
          "status": "RACING"
        },
        {
          "eElapsedR": 3720958,
          "eElapsedS": 3833434,
          "old": false,
          "eElapsedRFormatted": "43d 1h 35m 58s",
          "d24": 134500,
          "started": true,
          "finished": false,
          "eFinishS": 1769545474,
          "eFinishR": 1769432998,
          "ceElapsedRFormatted": "43d 1h 35m 58s",
          "eElapsedSFormatted": "44d 8h 50m 34s",
          "rankR": 25,
          "rankS": 25,
          "vmgS": 4.456211800757062,
          "cElapsedS": 3833434,
          "vmgR": 5.64452079540085,
          "tcf": "1.000",
          "cElapsedR": 3720958,
          "dtf": 661337,
          "ceElapsedSFormatted": "44d 8h 50m 34s",
          "id": 18,
          "dmg": 4463738,
          "status": "RACING"
        },
        {
          "eElapsedR": 3724937,
          "eElapsedS": 3850675,
          "old": false,
          "eElapsedRFormatted": "43d 2h 42m 17s",
          "d24": 131735,
          "started": true,
          "finished": false,
          "eFinishS": 1769561515,
          "eFinishR": 1769435777,
          "ceElapsedRFormatted": "43d 2h 42m 17s",
          "eElapsedSFormatted": "44d 13h 37m 55s",
          "rankR": 26,
          "rankS": 26,
          "vmgS": 4.436260092628173,
          "cElapsedS": 3850675,
          "vmgR": 5.750067729083994,
          "tcf": "1.000",
          "cElapsedR": 3724937,
          "dtf": 678144,
          "ceElapsedSFormatted": "44d 13h 37m 55s",
          "id": 8,
          "dmg": 4319817,
          "status": "RACING"
        },
        {
          "eElapsedR": 3737277,
          "eElapsedS": 3900838,
          "old": false,
          "eElapsedRFormatted": "43d 6h 7m 57s",
          "d24": 143738,
          "started": true,
          "finished": false,
          "eFinishS": 1769614318,
          "eFinishR": 1769450757,
          "ceElapsedRFormatted": "43d 6h 7m 57s",
          "eElapsedSFormatted": "45d 3h 33m 58s",
          "rankR": 27,
          "rankS": 27,
          "vmgS": 4.379211745141887,
          "cElapsedS": 3900838,
          "vmgR": 6.008749249667588,
          "tcf": "1.000",
          "cElapsedR": 3737277,
          "dtf": 733655,
          "ceElapsedSFormatted": "45d 3h 33m 58s",
          "id": 30,
          "dmg": 4267427,
          "status": "RACING"
        },
        {
          "eElapsedR": 3790234,
          "eElapsedS": 3953131,
          "old": false,
          "eElapsedRFormatted": "43d 20h 50m 34s",
          "d24": 137987,
          "started": true,
          "finished": false,
          "eFinishS": 1769664331,
          "eFinishR": 1769501434,
          "ceElapsedRFormatted": "43d 20h 50m 34s",
          "eElapsedSFormatted": "45d 18h 5m 31s",
          "rankR": 28,
          "rankS": 28,
          "vmgS": 4.321282731656091,
          "cElapsedS": 3953131,
          "vmgR": 5.757193648032995,
          "tcf": "1.000",
          "cElapsedR": 3790234,
          "dtf": 783982,
          "ceElapsedSFormatted": "45d 18h 5m 31s",
          "id": 11,
          "dmg": 4255140,
          "status": "RACING"
        },
        {
          "eElapsedR": 3867964,
          "eElapsedS": 3966469,
          "old": false,
          "eElapsedRFormatted": "44d 18h 26m 4s",
          "d24": 120810,
          "started": true,
          "finished": false,
          "eFinishS": 1769681389,
          "eFinishR": 1769582884,
          "ceElapsedRFormatted": "44d 18h 26m 4s",
          "eElapsedSFormatted": "45d 21h 47m 49s",
          "rankR": 29,
          "rankS": 29,
          "vmgS": 4.306751335719921,
          "cElapsedS": 3966469,
          "vmgR": 5.048850099663829,
          "tcf": "1.000",
          "cElapsedR": 3867964,
          "dtf": 801743,
          "ceElapsedSFormatted": "45d 21h 47m 49s",
          "id": 42,
          "dmg": 4219709,
          "status": "RACING"
        },
        {
          "eElapsedR": 3810715,
          "eElapsedS": 3974685,
          "old": false,
          "eElapsedRFormatted": "44d 2h 31m 55s",
          "d24": 137232,
          "started": true,
          "finished": false,
          "eFinishS": 1769684685,
          "eFinishR": 1769520715,
          "ceElapsedRFormatted": "44d 2h 31m 55s",
          "eElapsedSFormatted": "46d 0h 4m 45s",
          "rankR": 30,
          "rankS": 30,
          "vmgS": 4.2978489953566426,
          "cElapsedS": 3974685,
          "vmgR": 5.680991641355013,
          "tcf": "1.000",
          "cElapsedR": 3810715,
          "dtf": 804026,
          "ceElapsedSFormatted": "46d 0h 4m 45s",
          "id": 1,
          "dmg": 4257110,
          "status": "RACING"
        },
        {
          "eElapsedR": 4138795,
          "eElapsedS": 3993071,
          "old": false,
          "eElapsedRFormatted": "47d 21h 39m 55s",
          "d24": 97321,
          "started": true,
          "finished": false,
          "eFinishS": 1769703311,
          "eFinishR": 1769849035,
          "ceElapsedRFormatted": "47d 21h 39m 55s",
          "eElapsedSFormatted": "46d 5h 11m 11s",
          "rankR": 31,
          "rankS": 31,
          "vmgS": 4.278059158021288,
          "cElapsedS": 3993071,
          "vmgR": 3.533975017608192,
          "tcf": "1.000",
          "cElapsedR": 4138795,
          "dtf": 822464,
          "ceElapsedSFormatted": "46d 5h 11m 11s",
          "id": 3,
          "dmg": 4092705,
          "status": "RACING"
        },
        {
          "eElapsedR": 3974483,
          "eElapsedS": 4052858,
          "old": false,
          "eElapsedRFormatted": "46d 0h 1m 23s",
          "d24": 116397,
          "started": true,
          "finished": false,
          "eFinishS": 1769765618,
          "eFinishR": 1769687243,
          "ceElapsedRFormatted": "46d 0h 1m 23s",
          "eElapsedSFormatted": "46d 21h 47m 38s",
          "rankR": 32,
          "rankS": 32,
          "vmgS": 4.214950367275307,
          "cElapsedS": 4052858,
          "vmgR": 4.7036013424769685,
          "tcf": "1.000",
          "cElapsedR": 3974483,
          "dtf": 883281,
          "ceElapsedSFormatted": "46d 21h 47m 38s",
          "id": 24,
          "dmg": 4144897,
          "status": "RACING"
        },
        {
          "eElapsedR": 3824664,
          "eElapsedS": 4063431,
          "old": false,
          "eElapsedRFormatted": "44d 6h 24m 24s",
          "d24": 149934,
          "started": true,
          "finished": false,
          "eFinishS": 1769774391,
          "eFinishR": 1769535624,
          "ceElapsedRFormatted": "44d 6h 24m 24s",
          "eElapsedSFormatted": "47d 0h 43m 51s",
          "rankR": 33,
          "rankS": 33,
          "vmgS": 4.203983168976963,
          "cElapsedS": 4063431,
          "vmgR": 6.118045718700773,
          "tcf": "1.000",
          "cElapsedR": 3824664,
          "dtf": 891228,
          "ceElapsedSFormatted": "47d 0h 43m 51s",
          "id": 9,
          "dmg": 4188165,
          "status": "RACING"
        },
        {
          "eElapsedR": 4014069,
          "eElapsedS": 4102859,
          "old": false,
          "eElapsedRFormatted": "46d 11h 1m 9s",
          "d24": 111838,
          "started": true,
          "finished": false,
          "eFinishS": 1769816219,
          "eFinishR": 1769727429,
          "ceElapsedRFormatted": "46d 11h 1m 9s",
          "eElapsedSFormatted": "47d 11h 40m 59s",
          "rankR": 34,
          "rankS": 34,
          "vmgS": 4.163582738269205,
          "cElapsedS": 4102859,
          "vmgR": 4.6797424741563995,
          "tcf": "1.000",
          "cElapsedR": 4014069,
          "dtf": 931037,
          "ceElapsedSFormatted": "47d 11h 40m 59s",
          "id": 29,
          "dmg": 4058778,
          "status": "RACING"
        },
        {
          "eElapsedR": 3977786,
          "eElapsedS": 4102078,
          "old": false,
          "eElapsedRFormatted": "46d 0h 56m 26s",
          "d24": 112547,
          "started": true,
          "finished": false,
          "eFinishS": 1769816398,
          "eFinishR": 1769692106,
          "ceElapsedRFormatted": "46d 0h 56m 26s",
          "eElapsedSFormatted": "47d 11h 27m 58s",
          "rankR": 35,
          "rankS": 35,
          "vmgS": 4.164376116991251,
          "cElapsedS": 4102078,
          "vmgR": 4.924543020392141,
          "tcf": "1.000",
          "cElapsedR": 3977786,
          "dtf": 931425,
          "ceElapsedSFormatted": "47d 11h 27m 58s",
          "id": 37,
          "dmg": 4038887,
          "status": "RACING"
        },
        {
          "eElapsedR": 3995666,
          "eElapsedS": 4178350,
          "old": false,
          "eElapsedRFormatted": "46d 5h 54m 26s",
          "d24": 121706,
          "started": true,
          "finished": false,
          "eFinishS": 1769892430,
          "eFinishR": 1769709746,
          "ceElapsedRFormatted": "46d 5h 54m 26s",
          "eElapsedSFormatted": "48d 8h 39m 10s",
          "rankR": 36,
          "rankS": 36,
          "vmgS": 4.088358756113975,
          "cElapsedS": 4178350,
          "vmgR": 5.157604363824301,
          "tcf": "1.000",
          "cElapsedR": 3995666,
          "dtf": 1000733,
          "ceElapsedSFormatted": "48d 8h 39m 10s",
          "id": 35,
          "dmg": 3975340,
          "status": "RACING"
        },
        {
          "eElapsedR": 3900299,
          "eElapsedS": 4214770,
          "old": false,
          "eElapsedRFormatted": "45d 3h 24m 59s",
          "d24": 144404,
          "started": true,
          "finished": false,
          "eFinishS": 1769925370,
          "eFinishR": 1769610899,
          "ceElapsedRFormatted": "45d 3h 24m 59s",
          "eElapsedSFormatted": "48d 18h 46m 10s",
          "rankR": 37,
          "rankS": 37,
          "vmgS": 4.053031592346382,
          "cElapsedS": 4214770,
          "vmgR": 6.1783816903417375,
          "tcf": "1.000",
          "cElapsedR": 3900299,
          "dtf": 1029205,
          "ceElapsedSFormatted": "48d 18h 46m 10s",
          "id": 6,
          "dmg": 3964720,
          "status": "RACING"
        },
        {
          "eElapsedR": 4750591,
          "eElapsedS": 4360635,
          "old": false,
          "eElapsedRFormatted": "54d 23h 36m 31s",
          "d24": 73977,
          "started": true,
          "finished": false,
          "eFinishS": 1770071955,
          "eFinishR": 1770461911,
          "ceElapsedRFormatted": "54d 23h 36m 31s",
          "eElapsedSFormatted": "50d 11h 17m 15s",
          "rankR": 38,
          "rankS": 38,
          "vmgS": 3.9174560034206283,
          "cElapsedS": 4360635,
          "vmgR": 2.8644261039764984,
          "tcf": "1.000",
          "cElapsedR": 4750591,
          "dtf": 1154289,
          "ceElapsedSFormatted": "50d 11h 17m 15s",
          "id": 12,
          "dmg": 3954979,
          "status": "RACING"
        },
        {
          "eElapsedR": 4320744,
          "eElapsedS": 4641490,
          "old": false,
          "eElapsedRFormatted": "50d 0h 12m 24s",
          "d24": 121399,
          "started": true,
          "finished": false,
          "eFinishS": 1770356290,
          "eFinishR": 1770035544,
          "ceElapsedRFormatted": "50d 0h 12m 24s",
          "eElapsedSFormatted": "53d 17h 18m 10s",
          "rankR": 39,
          "rankS": 39,
          "vmgS": 3.6804118477750274,
          "cElapsedS": 4641490,
          "vmgR": 4.832843035890032,
          "tcf": "1.000",
          "cElapsedR": 4320744,
          "dtf": 1375129,
          "ceElapsedSFormatted": "53d 17h 18m 10s",
          "id": 41,
          "dmg": 3727073,
          "status": "RACING"
        },
        {
          "eElapsedR": 4671581,
          "eElapsedS": 4705249,
          "old": false,
          "eElapsedRFormatted": "54d 1h 39m 41s",
          "d24": 90187,
          "started": true,
          "finished": false,
          "eFinishS": 1770415609,
          "eFinishR": 1770381941,
          "ceElapsedRFormatted": "54d 1h 39m 41s",
          "eElapsedSFormatted": "54d 11h 0m 49s",
          "rankR": 40,
          "rankS": 40,
          "vmgS": 3.6305403095910003,
          "cElapsedS": 4705249,
          "vmgR": 3.719713634673218,
          "tcf": "1.000",
          "cElapsedR": 4671581,
          "dtf": 1416318,
          "ceElapsedSFormatted": "54d 11h 0m 49s",
          "id": 4,
          "dmg": 3613776,
          "status": "RACING"
        },
        {
          "eElapsedR": 4502416,
          "eElapsedS": 5126289,
          "old": false,
          "eElapsedRFormatted": "52d 2h 40m 16s",
          "d24": 122879,
          "started": true,
          "finished": false,
          "eFinishS": 1770840849,
          "eFinishR": 1770216976,
          "ceElapsedRFormatted": "52d 2h 40m 16s",
          "eElapsedSFormatted": "59d 7h 58m 9s",
          "rankR": 41,
          "rankS": 41,
          "vmgS": 3.3323514965830063,
          "cElapsedS": 5126289,
          "vmgR": 5.056529319039967,
          "tcf": "1.000",
          "cElapsedR": 4502416,
          "dtf": 1693615,
          "ceElapsedSFormatted": "59d 7h 58m 9s",
          "id": 39,
          "dmg": 3377164,
          "status": "RACING"
        },
        {
          "eElapsedR": 4900622,
          "eElapsedS": 5154400,
          "old": true,
          "eElapsedRFormatted": "56d 17h 17m 2s",
          "d24": 78739,
          "started": true,
          "finished": false,
          "eFinishS": 1770868600,
          "eFinishR": 1770614822,
          "ceElapsedRFormatted": "56d 17h 17m 2s",
          "eElapsedSFormatted": "59d 15h 46m 40s",
          "rankR": 42,
          "rankS": 42,
          "vmgS": 3.314177184989787,
          "cElapsedS": 5154400,
          "vmgR": 3.820476464517798,
          "tcf": "1.000",
          "cElapsedR": 4900622,
          "dtf": 1762937,
          "ceElapsedSFormatted": "59d 15h 46m 40s",
          "id": 36,
          "dmg": 4737279,
          "status": "RACING"
        },
        {
          "eElapsedR": 4638893,
          "eElapsedS": 5414507,
          "old": false,
          "eElapsedRFormatted": "53d 16h 34m 53s",
          "d24": 125763,
          "started": true,
          "finished": false,
          "eFinishS": 1771127507,
          "eFinishR": 1770351893,
          "ceElapsedRFormatted": "53d 16h 34m 53s",
          "eElapsedSFormatted": "62d 16h 1m 47s",
          "rankR": 43,
          "rankS": 43,
          "vmgS": 3.1549676679345415,
          "cElapsedS": 5414507,
          "vmgR": 4.980177652878837,
          "tcf": "1.000",
          "cElapsedR": 4638893,
          "dtf": 1854685,
          "ceElapsedSFormatted": "62d 16h 1m 47s",
          "id": 26,
          "dmg": 3278911,
          "status": "RACING"
        }
      ],
      "id": 78453,
      "type": "LEVEL"
    },
    {
      "teams": [
        {
          "eElapsedR": 3451296,
          "eElapsedS": 3483117,
          "old": false,
          "eElapsedRFormatted": "39d 22h 41m 36s",
          "d24": 132433,
          "started": true,
          "finished": false,
          "eFinishS": 1769197077,
          "eFinishR": 1769165256,
          "ceElapsedRFormatted": "39d 22h 41m 36s",
          "eElapsedSFormatted": "40d 7h 31m 57s",
          "rankR": 1,
          "rankS": 1,
          "vmgS": 4.904398613434057,
          "cElapsedS": 3483117,
          "vmgR": 5.967149759177435,
          "tcf": "1.000",
          "cElapsedR": 3451296,
          "dtf": 243410,
          "ceElapsedSFormatted": "40d 7h 31m 57s",
          "id": 34,
          "dmg": 4706738,
          "status": "RACING"
        },
        {
          "eElapsedR": 3506635,
          "eElapsedS": 3598089,
          "old": false,
          "eElapsedRFormatted": "40d 14h 3m 55s",
          "d24": 160142,
          "started": true,
          "finished": false,
          "eFinishS": 1769312769,
          "eFinishR": 1769221315,
          "ceElapsedRFormatted": "40d 14h 3m 55s",
          "eElapsedSFormatted": "41d 15h 28m 9s",
          "rankR": 2,
          "rankS": 2,
          "vmgS": 4.747685295103189,
          "cElapsedS": 3598089,
          "vmgR": 6.814209847289504,
          "tcf": "1.000",
          "cElapsedR": 3506635,
          "dtf": 397703,
          "ceElapsedSFormatted": "41d 15h 28m 9s",
          "id": 40,
          "dmg": 4558855,
          "status": "RACING"
        },
        {
          "eElapsedR": 3651117,
          "eElapsedS": 3781094,
          "old": false,
          "eElapsedRFormatted": "42d 6h 11m 57s",
          "d24": 146340,
          "started": true,
          "finished": false,
          "eFinishS": 1769495534,
          "eFinishR": 1769365557,
          "ceElapsedRFormatted": "42d 6h 11m 57s",
          "eElapsedSFormatted": "43d 18h 18m 14s",
          "rankR": 3,
          "rankS": 3,
          "vmgS": 4.517897032286437,
          "cElapsedS": 3781094,
          "vmgR": 6.1750718134451095,
          "tcf": "1.000",
          "cElapsedR": 3651117,
          "dtf": 607820,
          "ceElapsedSFormatted": "43d 18h 18m 14s",
          "id": 38,
          "dmg": 4336698,
          "status": "RACING"
        },
        {
          "eElapsedR": 3637102,
          "eElapsedS": 3807439,
          "old": false,
          "eElapsedRFormatted": "42d 2h 18m 22s",
          "d24": 158411,
          "started": true,
          "finished": false,
          "eFinishS": 1769522479,
          "eFinishR": 1769352142,
          "ceElapsedRFormatted": "42d 2h 18m 22s",
          "eElapsedSFormatted": "44d 1h 37m 19s",
          "rankR": 4,
          "rankS": 4,
          "vmgS": 4.486635960121709,
          "cElapsedS": 3807439,
          "vmgR": 6.728233220476782,
          "tcf": "1.000",
          "cElapsedR": 3637102,
          "dtf": 637195,
          "ceElapsedSFormatted": "44d 1h 37m 19s",
          "id": 43,
          "dmg": 4512241,
          "status": "RACING"
        },
        {
          "eElapsedR": 3867964,
          "eElapsedS": 3966469,
          "old": false,
          "eElapsedRFormatted": "44d 18h 26m 4s",
          "d24": 120810,
          "started": true,
          "finished": false,
          "eFinishS": 1769681389,
          "eFinishR": 1769582884,
          "ceElapsedRFormatted": "44d 18h 26m 4s",
          "eElapsedSFormatted": "45d 21h 47m 49s",
          "rankR": 5,
          "rankS": 5,
          "vmgS": 4.306751335719921,
          "cElapsedS": 3966469,
          "vmgR": 5.048850099663829,
          "tcf": "1.000",
          "cElapsedR": 3867964,
          "dtf": 801743,
          "ceElapsedSFormatted": "45d 21h 47m 49s",
          "id": 42,
          "dmg": 4219709,
          "status": "RACING"
        },
        {
          "eElapsedR": 3977786,
          "eElapsedS": 4102078,
          "old": false,
          "eElapsedRFormatted": "46d 0h 56m 26s",
          "d24": 112547,
          "started": true,
          "finished": false,
          "eFinishS": 1769816398,
          "eFinishR": 1769692106,
          "ceElapsedRFormatted": "46d 0h 56m 26s",
          "eElapsedSFormatted": "47d 11h 27m 58s",
          "rankR": 6,
          "rankS": 6,
          "vmgS": 4.164376116991251,
          "cElapsedS": 4102078,
          "vmgR": 4.924543020392141,
          "tcf": "1.000",
          "cElapsedR": 3977786,
          "dtf": 931425,
          "ceElapsedSFormatted": "47d 11h 27m 58s",
          "id": 37,
          "dmg": 4038887,
          "status": "RACING"
        },
        {
          "eElapsedR": 3995666,
          "eElapsedS": 4178350,
          "old": false,
          "eElapsedRFormatted": "46d 5h 54m 26s",
          "d24": 121706,
          "started": true,
          "finished": false,
          "eFinishS": 1769892430,
          "eFinishR": 1769709746,
          "ceElapsedRFormatted": "46d 5h 54m 26s",
          "eElapsedSFormatted": "48d 8h 39m 10s",
          "rankR": 7,
          "rankS": 7,
          "vmgS": 4.088358756113975,
          "cElapsedS": 4178350,
          "vmgR": 5.157604363824301,
          "tcf": "1.000",
          "cElapsedR": 3995666,
          "dtf": 1000733,
          "ceElapsedSFormatted": "48d 8h 39m 10s",
          "id": 35,
          "dmg": 3975340,
          "status": "RACING"
        },
        {
          "eElapsedR": 4320744,
          "eElapsedS": 4641490,
          "old": false,
          "eElapsedRFormatted": "50d 0h 12m 24s",
          "d24": 121399,
          "started": true,
          "finished": false,
          "eFinishS": 1770356290,
          "eFinishR": 1770035544,
          "ceElapsedRFormatted": "50d 0h 12m 24s",
          "eElapsedSFormatted": "53d 17h 18m 10s",
          "rankR": 8,
          "rankS": 8,
          "vmgS": 3.6804118477750274,
          "cElapsedS": 4641490,
          "vmgR": 4.832843035890032,
          "tcf": "1.000",
          "cElapsedR": 4320744,
          "dtf": 1375129,
          "ceElapsedSFormatted": "53d 17h 18m 10s",
          "id": 41,
          "dmg": 3727073,
          "status": "RACING"
        },
        {
          "eElapsedR": 4502416,
          "eElapsedS": 5126289,
          "old": false,
          "eElapsedRFormatted": "52d 2h 40m 16s",
          "d24": 122879,
          "started": true,
          "finished": false,
          "eFinishS": 1770840849,
          "eFinishR": 1770216976,
          "ceElapsedRFormatted": "52d 2h 40m 16s",
          "eElapsedSFormatted": "59d 7h 58m 9s",
          "rankR": 9,
          "rankS": 9,
          "vmgS": 3.3323514965830063,
          "cElapsedS": 5126289,
          "vmgR": 5.056529319039967,
          "tcf": "1.000",
          "cElapsedR": 4502416,
          "dtf": 1693615,
          "ceElapsedSFormatted": "59d 7h 58m 9s",
          "id": 39,
          "dmg": 3377164,
          "status": "RACING"
        },
        {
          "eElapsedR": 4900622,
          "eElapsedS": 5154400,
          "old": true,
          "eElapsedRFormatted": "56d 17h 17m 2s",
          "d24": 78739,
          "started": true,
          "finished": false,
          "eFinishS": 1770868600,
          "eFinishR": 1770614822,
          "ceElapsedRFormatted": "56d 17h 17m 2s",
          "eElapsedSFormatted": "59d 15h 46m 40s",
          "rankR": 10,
          "rankS": 10,
          "vmgS": 3.314177184989787,
          "cElapsedS": 5154400,
          "vmgR": 3.820476464517798,
          "tcf": "1.000",
          "cElapsedR": 4900622,
          "dtf": 1762937,
          "ceElapsedSFormatted": "59d 15h 46m 40s",
          "id": 36,
          "dmg": 4737279,
          "status": "RACING"
        }
      ],
      "id": 78454,
      "type": "LEVEL"
    },
    {
      "teams": [
        {
          "cElapsed": 3153480,
          "old": false,
          "d24": 157514,
          "started": true,
          "finished": true,
          "elapsed": 3153480,
          "cElapsedFormatted": "36d 11h 58m 0s",
          "rankR": 1,
          "rankS": 1,
          "tcf": "1.000",
          "dtf": 0,
          "id": 27,
          "finishAt": 1768866600,
          "elapsedFormatted": "36d 11h 58m 0s",
          "dmg": 4984428,
          "status": "RACING"
        },
        {
          "cElapsed": 3201180,
          "old": false,
          "d24": 140941,
          "started": true,
          "finished": true,
          "elapsed": 3201180,
          "cElapsedFormatted": "37d 1h 13m 0s",
          "rankR": 2,
          "rankS": 2,
          "tcf": "1.000",
          "dtf": 0,
          "id": 23,
          "finishAt": 1768913820,
          "elapsedFormatted": "37d 1h 13m 0s",
          "dmg": 4890226,
          "status": "RACING"
        },
        {
          "eElapsedR": 3327475,
          "eElapsedS": 3334151,
          "old": false,
          "eElapsedRFormatted": "38d 12h 17m 55s",
          "d24": 163977,
          "started": true,
          "finished": false,
          "eFinishS": 1769047031,
          "eFinishR": 1769040355,
          "ceElapsedRFormatted": "38d 12h 17m 55s",
          "eElapsedSFormatted": "38d 14h 9m 11s",
          "rankR": 3,
          "rankS": 3,
          "vmgS": 5.123521558518877,
          "cElapsedS": 3334151,
          "vmgR": 7.308248235976361,
          "tcf": "1.000",
          "cElapsedR": 3327475,
          "dtf": 31782,
          "ceElapsedSFormatted": "38d 14h 9m 11s",
          "id": 25,
          "dmg": 5030946,
          "status": "RACING"
        },
        {
          "eElapsedR": 3414797,
          "eElapsedS": 3447793,
          "old": false,
          "eElapsedRFormatted": "39d 12h 33m 17s",
          "d24": 144177,
          "started": true,
          "finished": false,
          "eFinishS": 1769161633,
          "eFinishR": 1769128637,
          "ceElapsedRFormatted": "39d 12h 33m 17s",
          "eElapsedSFormatted": "39d 21h 43m 13s",
          "rankR": 4,
          "rankS": 4,
          "vmgS": 4.954646365753952,
          "cElapsedS": 3447793,
          "vmgR": 6.437748252972931,
          "tcf": "1.000",
          "cElapsedR": 3414797,
          "dtf": 197123,
          "ceElapsedSFormatted": "39d 21h 43m 13s",
          "id": 33,
          "dmg": 4757377,
          "status": "RACING"
        },
        {
          "eElapsedR": 3610724,
          "eElapsedS": 3717665,
          "old": false,
          "eElapsedRFormatted": "41d 18h 58m 44s",
          "d24": 143682,
          "started": true,
          "finished": false,
          "eFinishS": 1769431385,
          "eFinishR": 1769324444,
          "ceElapsedRFormatted": "41d 18h 58m 44s",
          "eElapsedSFormatted": "43d 0h 41m 5s",
          "rankR": 5,
          "rankS": 5,
          "vmgS": 4.59497961354953,
          "cElapsedS": 3717665,
          "vmgR": 6.163729589426269,
          "tcf": "1.000",
          "cElapsedR": 3610724,
          "dtf": 536311,
          "ceElapsedSFormatted": "43d 0h 41m 5s",
          "id": 32,
          "dmg": 4387043,
          "status": "RACING"
        },
        {
          "eElapsedR": 3599379,
          "eElapsedS": 3721994,
          "old": false,
          "eElapsedRFormatted": "41d 15h 49m 39s",
          "d24": 154072,
          "started": true,
          "finished": false,
          "eFinishS": 1769435594,
          "eFinishR": 1769312979,
          "ceElapsedRFormatted": "41d 15h 49m 39s",
          "eElapsedSFormatted": "43d 1h 53m 14s",
          "rankR": 6,
          "rankS": 6,
          "vmgS": 4.5896352676235885,
          "cElapsedS": 3721994,
          "vmgR": 6.454458333249591,
          "tcf": "1.000",
          "cElapsedR": 3599379,
          "dtf": 541053,
          "ceElapsedSFormatted": "43d 1h 53m 14s",
          "id": 31,
          "dmg": 4415360,
          "status": "RACING"
        },
        {
          "eElapsedR": 3674435,
          "eElapsedS": 3780013,
          "old": false,
          "eElapsedRFormatted": "42d 12h 40m 35s",
          "d24": 141285,
          "started": true,
          "finished": false,
          "eFinishS": 1769493253,
          "eFinishR": 1769387675,
          "ceElapsedRFormatted": "42d 12h 40m 35s",
          "eElapsedSFormatted": "43d 18h 0m 13s",
          "rankR": 7,
          "rankS": 7,
          "vmgS": 4.519189013600028,
          "cElapsedS": 3780013,
          "vmgR": 5.786640141411118,
          "tcf": "1.000",
          "cElapsedR": 3674435,
          "dtf": 605099,
          "ceElapsedSFormatted": "43d 18h 0m 13s",
          "id": 28,
          "dmg": 4390195,
          "status": "RACING"
        },
        {
          "eElapsedR": 3737277,
          "eElapsedS": 3900838,
          "old": false,
          "eElapsedRFormatted": "43d 6h 7m 57s",
          "d24": 143738,
          "started": true,
          "finished": false,
          "eFinishS": 1769614318,
          "eFinishR": 1769450757,
          "ceElapsedRFormatted": "43d 6h 7m 57s",
          "eElapsedSFormatted": "45d 3h 33m 58s",
          "rankR": 8,
          "rankS": 8,
          "vmgS": 4.379211745141887,
          "cElapsedS": 3900838,
          "vmgR": 6.008749249667588,
          "tcf": "1.000",
          "cElapsedR": 3737277,
          "dtf": 733655,
          "ceElapsedSFormatted": "45d 3h 33m 58s",
          "id": 30,
          "dmg": 4267427,
          "status": "RACING"
        },
        {
          "eElapsedR": 3974483,
          "eElapsedS": 4052858,
          "old": false,
          "eElapsedRFormatted": "46d 0h 1m 23s",
          "d24": 116397,
          "started": true,
          "finished": false,
          "eFinishS": 1769765618,
          "eFinishR": 1769687243,
          "ceElapsedRFormatted": "46d 0h 1m 23s",
          "eElapsedSFormatted": "46d 21h 47m 38s",
          "rankR": 9,
          "rankS": 9,
          "vmgS": 4.214950367275307,
          "cElapsedS": 4052858,
          "vmgR": 4.7036013424769685,
          "tcf": "1.000",
          "cElapsedR": 3974483,
          "dtf": 883281,
          "ceElapsedSFormatted": "46d 21h 47m 38s",
          "id": 24,
          "dmg": 4144897,
          "status": "RACING"
        },
        {
          "eElapsedR": 4014069,
          "eElapsedS": 4102859,
          "old": false,
          "eElapsedRFormatted": "46d 11h 1m 9s",
          "d24": 111838,
          "started": true,
          "finished": false,
          "eFinishS": 1769816219,
          "eFinishR": 1769727429,
          "ceElapsedRFormatted": "46d 11h 1m 9s",
          "eElapsedSFormatted": "47d 11h 40m 59s",
          "rankR": 10,
          "rankS": 10,
          "vmgS": 4.163582738269205,
          "cElapsedS": 4102859,
          "vmgR": 4.6797424741563995,
          "tcf": "1.000",
          "cElapsedR": 4014069,
          "dtf": 931037,
          "ceElapsedSFormatted": "47d 11h 40m 59s",
          "id": 29,
          "dmg": 4058778,
          "status": "RACING"
        },
        {
          "eElapsedR": 4638893,
          "eElapsedS": 5414507,
          "old": false,
          "eElapsedRFormatted": "53d 16h 34m 53s",
          "d24": 125763,
          "started": true,
          "finished": false,
          "eFinishS": 1771127507,
          "eFinishR": 1770351893,
          "ceElapsedRFormatted": "53d 16h 34m 53s",
          "eElapsedSFormatted": "62d 16h 1m 47s",
          "rankR": 11,
          "rankS": 11,
          "vmgS": 3.1549676679345415,
          "cElapsedS": 5414507,
          "vmgR": 4.980177652878837,
          "tcf": "1.000",
          "cElapsedR": 4638893,
          "dtf": 1854685,
          "ceElapsedSFormatted": "62d 16h 1m 47s",
          "id": 26,
          "dmg": 3278911,
          "status": "RACING"
        }
      ],
      "id": 78455,
      "type": "LEVEL"
    },
    {
      "teams": [
        {
          "cElapsed": 3065400,
          "old": false,
          "d24": 168055,
          "started": true,
          "finished": true,
          "elapsed": 3065400,
          "cElapsedFormatted": "35d 11h 30m 0s",
          "rankR": 1,
          "rankS": 1,
          "tcf": "1.000",
          "dtf": 0,
          "id": 19,
          "finishAt": 1768777560,
          "elapsedFormatted": "35d 11h 30m 0s",
          "dmg": 5003931,
          "status": "RACING"
        },
        {
          "eElapsedR": 3362153,
          "eElapsedS": 3372818,
          "old": false,
          "eElapsedRFormatted": "38d 21h 55m 53s",
          "d24": 140011,
          "started": true,
          "finished": false,
          "eFinishS": 1769084738,
          "eFinishR": 1769074073,
          "ceElapsedRFormatted": "38d 21h 55m 53s",
          "eElapsedSFormatted": "39d 0h 53m 38s",
          "rankR": 2,
          "rankS": 2,
          "vmgS": 5.064783813655568,
          "cElapsedS": 3372818,
          "vmgR": 6.102153211971003,
          "tcf": "1.000",
          "cElapsedR": 3362153,
          "dtf": 88264,
          "ceElapsedSFormatted": "39d 0h 53m 38s",
          "id": 17,
          "dmg": 4916730,
          "status": "RACING"
        },
        {
          "eElapsedR": 3526940,
          "eElapsedS": 3597361,
          "old": false,
          "eElapsedRFormatted": "40d 19h 42m 20s",
          "d24": 151585,
          "started": true,
          "finished": false,
          "eFinishS": 1769309761,
          "eFinishR": 1769239340,
          "ceElapsedRFormatted": "40d 19h 42m 20s",
          "eElapsedSFormatted": "41d 15h 16m 1s",
          "rankR": 3,
          "rankS": 3,
          "vmgS": 4.748645860990097,
          "cElapsedS": 3597361,
          "vmgR": 6.214537886290416,
          "tcf": "1.000",
          "cElapsedR": 3526940,
          "dtf": 393800,
          "ceElapsedSFormatted": "41d 15h 16m 1s",
          "id": 21,
          "dmg": 4619900,
          "status": "RACING"
        },
        {
          "eElapsedR": 3631008,
          "eElapsedS": 3717527,
          "old": false,
          "eElapsedRFormatted": "42d 0h 36m 48s",
          "d24": 135216,
          "started": true,
          "finished": false,
          "eFinishS": 1769430047,
          "eFinishR": 1769343528,
          "ceElapsedRFormatted": "42d 0h 36m 48s",
          "eElapsedSFormatted": "43d 0h 38m 47s",
          "rankR": 4,
          "rankS": 4,
          "vmgS": 4.595150129916895,
          "cElapsedS": 3717527,
          "vmgR": 5.791479037351371,
          "tcf": "1.000",
          "cElapsedR": 3631008,
          "dtf": 534622,
          "ceElapsedSFormatted": "43d 0h 38m 47s",
          "id": 22,
          "dmg": 4543260,
          "status": "RACING"
        },
        {
          "eElapsedR": 3648651,
          "eElapsedS": 3781209,
          "old": false,
          "eElapsedRFormatted": "42d 5h 30m 51s",
          "d24": 146040,
          "started": true,
          "finished": false,
          "eFinishS": 1769493489,
          "eFinishR": 1769360931,
          "ceElapsedRFormatted": "42d 5h 30m 51s",
          "eElapsedSFormatted": "43d 18h 20m 9s",
          "rankR": 5,
          "rankS": 5,
          "vmgS": 4.517760148038581,
          "cElapsedS": 3781209,
          "vmgR": 6.230140755585879,
          "tcf": "1.000",
          "cElapsedR": 3648651,
          "dtf": 605234,
          "ceElapsedSFormatted": "43d 18h 20m 9s",
          "id": 20,
          "dmg": 4481049,
          "status": "RACING"
        },
        {
          "eElapsedR": 3720958,
          "eElapsedS": 3833434,
          "old": false,
          "eElapsedRFormatted": "43d 1h 35m 58s",
          "d24": 134500,
          "started": true,
          "finished": false,
          "eFinishS": 1769545474,
          "eFinishR": 1769432998,
          "ceElapsedRFormatted": "43d 1h 35m 58s",
          "eElapsedSFormatted": "44d 8h 50m 34s",
          "rankR": 6,
          "rankS": 6,
          "vmgS": 4.456211800757062,
          "cElapsedS": 3833434,
          "vmgR": 5.64452079540085,
          "tcf": "1.000",
          "cElapsedR": 3720958,
          "dtf": 661337,
          "ceElapsedSFormatted": "44d 8h 50m 34s",
          "id": 18,
          "dmg": 4463738,
          "status": "RACING"
        }
      ],
      "id": 78456,
      "type": "LEVEL"
    },
    {
      "teams": [
        {
          "cElapsed": 2707680,
          "old": false,
          "d24": 128771,
          "started": true,
          "finished": true,
          "elapsed": 2707680,
          "cElapsedFormatted": "31d 8h 8m 0s",
          "rankR": 1,
          "rankS": 1,
          "tcf": "1.000",
          "dtf": 0,
          "id": 14,
          "finishAt": 1768419240,
          "elapsedFormatted": "31d 8h 8m 0s",
          "dmg": 4961713,
          "status": "RACING"
        },
        {
          "cElapsed": 2802060,
          "old": false,
          "d24": 154195,
          "started": true,
          "finished": true,
          "elapsed": 2802060,
          "cElapsedFormatted": "32d 10h 21m 0s",
          "rankR": 2,
          "rankS": 2,
          "tcf": "1.000",
          "dtf": 0,
          "id": 16,
          "finishAt": 1768513860,
          "elapsedFormatted": "32d 10h 21m 0s",
          "dmg": 4970999,
          "status": "RACING"
        },
        {
          "cElapsed": 2945460,
          "old": false,
          "d24": 131402,
          "started": true,
          "finished": true,
          "elapsed": 2945460,
          "cElapsedFormatted": "34d 2h 11m 0s",
          "rankR": 3,
          "rankS": 3,
          "tcf": "1.000",
          "dtf": 0,
          "id": 15,
          "finishAt": 1768657140,
          "elapsedFormatted": "34d 2h 11m 0s",
          "dmg": 4966715,
          "status": "RACING"
        },
        {
          "cElapsed": 3033900,
          "old": false,
          "d24": 107116,
          "started": true,
          "finished": true,
          "elapsed": 3033900,
          "cElapsedFormatted": "35d 2h 45m 0s",
          "rankR": 4,
          "rankS": 4,
          "tcf": "1.000",
          "dtf": 0,
          "id": 2,
          "finishAt": 1768744020,
          "elapsedFormatted": "35d 2h 45m 0s",
          "dmg": 4933692,
          "status": "RACING"
        },
        {
          "cElapsed": 3193380,
          "old": false,
          "d24": 148902,
          "started": true,
          "finished": true,
          "elapsed": 3193380,
          "cElapsedFormatted": "36d 23h 3m 0s",
          "rankR": 5,
          "rankS": 5,
          "tcf": "1.000",
          "dtf": 0,
          "id": 13,
          "finishAt": 1768904820,
          "elapsedFormatted": "36d 23h 3m 0s",
          "dmg": 4975343,
          "status": "RACING"
        },
        {
          "cElapsed": 3297600,
          "old": false,
          "d24": 152344,
          "started": true,
          "finished": true,
          "elapsed": 3297600,
          "cElapsedFormatted": "38d 4h 0m 0s",
          "rankR": 6,
          "rankS": 6,
          "tcf": "1.000",
          "dtf": 0,
          "id": 7,
          "finishAt": 1769008320,
          "elapsedFormatted": "38d 4h 0m 0s",
          "dmg": 4987043,
          "status": "RACING"
        },
        {
          "eElapsedR": 3316860,
          "eElapsedS": 3317362,
          "old": false,
          "eElapsedRFormatted": "38d 9h 21m 0s",
          "d24": 142693,
          "started": true,
          "finished": false,
          "eFinishS": 1769028442,
          "eFinishR": 1769027940,
          "ceElapsedRFormatted": "38d 9h 21m 0s",
          "eElapsedSFormatted": "38d 9h 29m 22s",
          "rankR": 7,
          "rankS": 7,
          "vmgS": 5.149450767100888,
          "cElapsedS": 3317362,
          "vmgR": 5.948656187188626,
          "tcf": "1.000",
          "cElapsedR": 3316860,
          "dtf": 5353,
          "ceElapsedSFormatted": "38d 9h 29m 22s",
          "id": 10,
          "dmg": 4983163,
          "status": "RACING"
        },
        {
          "eElapsedR": 3442813,
          "eElapsedS": 3489919,
          "old": false,
          "eElapsedRFormatted": "39d 20h 20m 13s",
          "d24": 138927,
          "started": true,
          "finished": false,
          "eFinishS": 1769200399,
          "eFinishR": 1769153293,
          "ceElapsedRFormatted": "39d 20h 20m 13s",
          "eElapsedSFormatted": "40d 9h 25m 19s",
          "rankR": 8,
          "rankS": 8,
          "vmgS": 4.894840473735954,
          "cElapsedS": 3489919,
          "vmgR": 6.6041586622066575,
          "tcf": "1.000",
          "cElapsedR": 3442813,
          "dtf": 247460,
          "ceElapsedSFormatted": "40d 9h 25m 19s",
          "id": 5,
          "dmg": 4776675,
          "status": "RACING"
        },
        {
          "eElapsedR": 3724937,
          "eElapsedS": 3850675,
          "old": false,
          "eElapsedRFormatted": "43d 2h 42m 17s",
          "d24": 131735,
          "started": true,
          "finished": false,
          "eFinishS": 1769561515,
          "eFinishR": 1769435777,
          "ceElapsedRFormatted": "43d 2h 42m 17s",
          "eElapsedSFormatted": "44d 13h 37m 55s",
          "rankR": 9,
          "rankS": 9,
          "vmgS": 4.436260092628173,
          "cElapsedS": 3850675,
          "vmgR": 5.750067729083994,
          "tcf": "1.000",
          "cElapsedR": 3724937,
          "dtf": 678144,
          "ceElapsedSFormatted": "44d 13h 37m 55s",
          "id": 8,
          "dmg": 4319817,
          "status": "RACING"
        },
        {
          "eElapsedR": 3790234,
          "eElapsedS": 3953131,
          "old": false,
          "eElapsedRFormatted": "43d 20h 50m 34s",
          "d24": 137987,
          "started": true,
          "finished": false,
          "eFinishS": 1769664331,
          "eFinishR": 1769501434,
          "ceElapsedRFormatted": "43d 20h 50m 34s",
          "eElapsedSFormatted": "45d 18h 5m 31s",
          "rankR": 10,
          "rankS": 10,
          "vmgS": 4.321282731656091,
          "cElapsedS": 3953131,
          "vmgR": 5.757193648032995,
          "tcf": "1.000",
          "cElapsedR": 3790234,
          "dtf": 783982,
          "ceElapsedSFormatted": "45d 18h 5m 31s",
          "id": 11,
          "dmg": 4255140,
          "status": "RACING"
        },
        {
          "eElapsedR": 3810715,
          "eElapsedS": 3974685,
          "old": false,
          "eElapsedRFormatted": "44d 2h 31m 55s",
          "d24": 137232,
          "started": true,
          "finished": false,
          "eFinishS": 1769684685,
          "eFinishR": 1769520715,
          "ceElapsedRFormatted": "44d 2h 31m 55s",
          "eElapsedSFormatted": "46d 0h 4m 45s",
          "rankR": 11,
          "rankS": 11,
          "vmgS": 4.2978489953566426,
          "cElapsedS": 3974685,
          "vmgR": 5.680991641355013,
          "tcf": "1.000",
          "cElapsedR": 3810715,
          "dtf": 804026,
          "ceElapsedSFormatted": "46d 0h 4m 45s",
          "id": 1,
          "dmg": 4257110,
          "status": "RACING"
        },
        {
          "eElapsedR": 4138795,
          "eElapsedS": 3993071,
          "old": false,
          "eElapsedRFormatted": "47d 21h 39m 55s",
          "d24": 97321,
          "started": true,
          "finished": false,
          "eFinishS": 1769703311,
          "eFinishR": 1769849035,
          "ceElapsedRFormatted": "47d 21h 39m 55s",
          "eElapsedSFormatted": "46d 5h 11m 11s",
          "rankR": 12,
          "rankS": 12,
          "vmgS": 4.278059158021288,
          "cElapsedS": 3993071,
          "vmgR": 3.533975017608192,
          "tcf": "1.000",
          "cElapsedR": 4138795,
          "dtf": 822464,
          "ceElapsedSFormatted": "46d 5h 11m 11s",
          "id": 3,
          "dmg": 4092705,
          "status": "RACING"
        },
        {
          "eElapsedR": 3824664,
          "eElapsedS": 4063431,
          "old": false,
          "eElapsedRFormatted": "44d 6h 24m 24s",
          "d24": 149934,
          "started": true,
          "finished": false,
          "eFinishS": 1769774391,
          "eFinishR": 1769535624,
          "ceElapsedRFormatted": "44d 6h 24m 24s",
          "eElapsedSFormatted": "47d 0h 43m 51s",
          "rankR": 13,
          "rankS": 13,
          "vmgS": 4.203983168976963,
          "cElapsedS": 4063431,
          "vmgR": 6.118045718700773,
          "tcf": "1.000",
          "cElapsedR": 3824664,
          "dtf": 891228,
          "ceElapsedSFormatted": "47d 0h 43m 51s",
          "id": 9,
          "dmg": 4188165,
          "status": "RACING"
        },
        {
          "eElapsedR": 3900299,
          "eElapsedS": 4214770,
          "old": false,
          "eElapsedRFormatted": "45d 3h 24m 59s",
          "d24": 144404,
          "started": true,
          "finished": false,
          "eFinishS": 1769925370,
          "eFinishR": 1769610899,
          "ceElapsedRFormatted": "45d 3h 24m 59s",
          "eElapsedSFormatted": "48d 18h 46m 10s",
          "rankR": 14,
          "rankS": 14,
          "vmgS": 4.053031592346382,
          "cElapsedS": 4214770,
          "vmgR": 6.1783816903417375,
          "tcf": "1.000",
          "cElapsedR": 3900299,
          "dtf": 1029205,
          "ceElapsedSFormatted": "48d 18h 46m 10s",
          "id": 6,
          "dmg": 3964720,
          "status": "RACING"
        },
        {
          "eElapsedR": 4750591,
          "eElapsedS": 4360635,
          "old": false,
          "eElapsedRFormatted": "54d 23h 36m 31s",
          "d24": 73977,
          "started": true,
          "finished": false,
          "eFinishS": 1770071955,
          "eFinishR": 1770461911,
          "ceElapsedRFormatted": "54d 23h 36m 31s",
          "eElapsedSFormatted": "50d 11h 17m 15s",
          "rankR": 15,
          "rankS": 15,
          "vmgS": 3.9174560034206283,
          "cElapsedS": 4360635,
          "vmgR": 2.8644261039764984,
          "tcf": "1.000",
          "cElapsedR": 4750591,
          "dtf": 1154289,
          "ceElapsedSFormatted": "50d 11h 17m 15s",
          "id": 12,
          "dmg": 3954979,
          "status": "RACING"
        },
        {
          "eElapsedR": 4671581,
          "eElapsedS": 4705249,
          "old": false,
          "eElapsedRFormatted": "54d 1h 39m 41s",
          "d24": 90187,
          "started": true,
          "finished": false,
          "eFinishS": 1770415609,
          "eFinishR": 1770381941,
          "ceElapsedRFormatted": "54d 1h 39m 41s",
          "eElapsedSFormatted": "54d 11h 0m 49s",
          "rankR": 16,
          "rankS": 16,
          "vmgS": 3.6305403095910003,
          "cElapsedS": 4705249,
          "vmgR": 3.719713634673218,
          "tcf": "1.000",
          "cElapsedR": 4671581,
          "dtf": 1416318,
          "ceElapsedSFormatted": "54d 11h 0m 49s",
          "id": 4,
          "dmg": 3613776,
          "status": "RACING"
        }
      ],
      "id": 78457,
      "type": "LEVEL"
    },
    {
      "teams": [
        {
          "eElapsedR": 3327475,
          "eElapsedS": 3334151,
          "old": false,
          "eElapsedRFormatted": "38d 12h 17m 55s",
          "d24": 163977,
          "started": true,
          "finished": false,
          "eFinishS": 1769047031,
          "eFinishR": 1769040355,
          "ceElapsedRFormatted": "38d 12h 17m 55s",
          "eElapsedSFormatted": "38d 14h 9m 11s",
          "rankR": 1,
          "rankS": 1,
          "vmgS": 5.123521558518877,
          "cElapsedS": 3334151,
          "vmgR": 7.308248235976361,
          "tcf": "1.000",
          "cElapsedR": 3327475,
          "dtf": 31782,
          "ceElapsedSFormatted": "38d 14h 9m 11s",
          "id": 25,
          "dmg": 5030946,
          "status": "RACING"
        },
        {
          "eElapsedR": 3631008,
          "eElapsedS": 3717527,
          "old": false,
          "eElapsedRFormatted": "42d 0h 36m 48s",
          "d24": 135216,
          "started": true,
          "finished": false,
          "eFinishS": 1769430047,
          "eFinishR": 1769343528,
          "ceElapsedRFormatted": "42d 0h 36m 48s",
          "eElapsedSFormatted": "43d 0h 38m 47s",
          "rankR": 2,
          "rankS": 2,
          "vmgS": 4.595150129916895,
          "cElapsedS": 3717527,
          "vmgR": 5.791479037351371,
          "tcf": "1.000",
          "cElapsedR": 3631008,
          "dtf": 534622,
          "ceElapsedSFormatted": "43d 0h 38m 47s",
          "id": 22,
          "dmg": 4543260,
          "status": "RACING"
        },
        {
          "eElapsedR": 3724937,
          "eElapsedS": 3850675,
          "old": false,
          "eElapsedRFormatted": "43d 2h 42m 17s",
          "d24": 131735,
          "started": true,
          "finished": false,
          "eFinishS": 1769561515,
          "eFinishR": 1769435777,
          "ceElapsedRFormatted": "43d 2h 42m 17s",
          "eElapsedSFormatted": "44d 13h 37m 55s",
          "rankR": 3,
          "rankS": 3,
          "vmgS": 4.436260092628173,
          "cElapsedS": 3850675,
          "vmgR": 5.750067729083994,
          "tcf": "1.000",
          "cElapsedR": 3724937,
          "dtf": 678144,
          "ceElapsedSFormatted": "44d 13h 37m 55s",
          "id": 8,
          "dmg": 4319817,
          "status": "RACING"
        },
        {
          "eElapsedR": 3867964,
          "eElapsedS": 3966469,
          "old": false,
          "eElapsedRFormatted": "44d 18h 26m 4s",
          "d24": 120810,
          "started": true,
          "finished": false,
          "eFinishS": 1769681389,
          "eFinishR": 1769582884,
          "ceElapsedRFormatted": "44d 18h 26m 4s",
          "eElapsedSFormatted": "45d 21h 47m 49s",
          "rankR": 4,
          "rankS": 4,
          "vmgS": 4.306751335719921,
          "cElapsedS": 3966469,
          "vmgR": 5.048850099663829,
          "tcf": "1.000",
          "cElapsedR": 3867964,
          "dtf": 801743,
          "ceElapsedSFormatted": "45d 21h 47m 49s",
          "id": 42,
          "dmg": 4219709,
          "status": "RACING"
        },
        {
          "eElapsedR": 3810715,
          "eElapsedS": 3974685,
          "old": false,
          "eElapsedRFormatted": "44d 2h 31m 55s",
          "d24": 137232,
          "started": true,
          "finished": false,
          "eFinishS": 1769684685,
          "eFinishR": 1769520715,
          "ceElapsedRFormatted": "44d 2h 31m 55s",
          "eElapsedSFormatted": "46d 0h 4m 45s",
          "rankR": 5,
          "rankS": 5,
          "vmgS": 4.2978489953566426,
          "cElapsedS": 3974685,
          "vmgR": 5.680991641355013,
          "tcf": "1.000",
          "cElapsedR": 3810715,
          "dtf": 804026,
          "ceElapsedSFormatted": "46d 0h 4m 45s",
          "id": 1,
          "dmg": 4257110,
          "status": "RACING"
        },
        {
          "eElapsedR": 3977786,
          "eElapsedS": 4102078,
          "old": false,
          "eElapsedRFormatted": "46d 0h 56m 26s",
          "d24": 112547,
          "started": true,
          "finished": false,
          "eFinishS": 1769816398,
          "eFinishR": 1769692106,
          "ceElapsedRFormatted": "46d 0h 56m 26s",
          "eElapsedSFormatted": "47d 11h 27m 58s",
          "rankR": 6,
          "rankS": 6,
          "vmgS": 4.164376116991251,
          "cElapsedS": 4102078,
          "vmgR": 4.924543020392141,
          "tcf": "1.000",
          "cElapsedR": 3977786,
          "dtf": 931425,
          "ceElapsedSFormatted": "47d 11h 27m 58s",
          "id": 37,
          "dmg": 4038887,
          "status": "RACING"
        },
        {
          "eElapsedR": 3900299,
          "eElapsedS": 4214770,
          "old": false,
          "eElapsedRFormatted": "45d 3h 24m 59s",
          "d24": 144404,
          "started": true,
          "finished": false,
          "eFinishS": 1769925370,
          "eFinishR": 1769610899,
          "ceElapsedRFormatted": "45d 3h 24m 59s",
          "eElapsedSFormatted": "48d 18h 46m 10s",
          "rankR": 7,
          "rankS": 7,
          "vmgS": 4.053031592346382,
          "cElapsedS": 4214770,
          "vmgR": 6.1783816903417375,
          "tcf": "1.000",
          "cElapsedR": 3900299,
          "dtf": 1029205,
          "ceElapsedSFormatted": "48d 18h 46m 10s",
          "id": 6,
          "dmg": 3964720,
          "status": "RACING"
        },
        {
          "eElapsedR": 4750591,
          "eElapsedS": 4360635,
          "old": false,
          "eElapsedRFormatted": "54d 23h 36m 31s",
          "d24": 73977,
          "started": true,
          "finished": false,
          "eFinishS": 1770071955,
          "eFinishR": 1770461911,
          "ceElapsedRFormatted": "54d 23h 36m 31s",
          "eElapsedSFormatted": "50d 11h 17m 15s",
          "rankR": 8,
          "rankS": 8,
          "vmgS": 3.9174560034206283,
          "cElapsedS": 4360635,
          "vmgR": 2.8644261039764984,
          "tcf": "1.000",
          "cElapsedR": 4750591,
          "dtf": 1154289,
          "ceElapsedSFormatted": "50d 11h 17m 15s",
          "id": 12,
          "dmg": 3954979,
          "status": "RACING"
        },
        {
          "eElapsedR": 4671581,
          "eElapsedS": 4705249,
          "old": false,
          "eElapsedRFormatted": "54d 1h 39m 41s",
          "d24": 90187,
          "started": true,
          "finished": false,
          "eFinishS": 1770415609,
          "eFinishR": 1770381941,
          "ceElapsedRFormatted": "54d 1h 39m 41s",
          "eElapsedSFormatted": "54d 11h 0m 49s",
          "rankR": 9,
          "rankS": 9,
          "vmgS": 3.6305403095910003,
          "cElapsedS": 4705249,
          "vmgR": 3.719713634673218,
          "tcf": "1.000",
          "cElapsedR": 4671581,
          "dtf": 1416318,
          "ceElapsedSFormatted": "54d 11h 0m 49s",
          "id": 4,
          "dmg": 3613776,
          "status": "RACING"
        }
      ],
      "id": 78458,
      "type": "LEVEL"
    },
    {
      "teams": [
        {
          "eElapsedR": 3526940,
          "eElapsedS": 3597361,
          "old": false,
          "eElapsedRFormatted": "40d 19h 42m 20s",
          "d24": 151585,
          "started": true,
          "finished": false,
          "eFinishS": 1769309761,
          "eFinishR": 1769239340,
          "ceElapsedRFormatted": "40d 19h 42m 20s",
          "eElapsedSFormatted": "41d 15h 16m 1s",
          "rankR": 1,
          "rankS": 1,
          "vmgS": 4.748645860990097,
          "cElapsedS": 3597361,
          "vmgR": 6.214537886290416,
          "tcf": "1.000",
          "cElapsedR": 3526940,
          "dtf": 393800,
          "ceElapsedSFormatted": "41d 15h 16m 1s",
          "id": 21,
          "dmg": 4619900,
          "status": "RACING"
        },
        {
          "eElapsedR": 3599379,
          "eElapsedS": 3721994,
          "old": false,
          "eElapsedRFormatted": "41d 15h 49m 39s",
          "d24": 154072,
          "started": true,
          "finished": false,
          "eFinishS": 1769435594,
          "eFinishR": 1769312979,
          "ceElapsedRFormatted": "41d 15h 49m 39s",
          "eElapsedSFormatted": "43d 1h 53m 14s",
          "rankR": 2,
          "rankS": 2,
          "vmgS": 4.5896352676235885,
          "cElapsedS": 3721994,
          "vmgR": 6.454458333249591,
          "tcf": "1.000",
          "cElapsedR": 3599379,
          "dtf": 541053,
          "ceElapsedSFormatted": "43d 1h 53m 14s",
          "id": 31,
          "dmg": 4415360,
          "status": "RACING"
        },
        {
          "eElapsedR": 3648651,
          "eElapsedS": 3781209,
          "old": false,
          "eElapsedRFormatted": "42d 5h 30m 51s",
          "d24": 146040,
          "started": true,
          "finished": false,
          "eFinishS": 1769493489,
          "eFinishR": 1769360931,
          "ceElapsedRFormatted": "42d 5h 30m 51s",
          "eElapsedSFormatted": "43d 18h 20m 9s",
          "rankR": 3,
          "rankS": 3,
          "vmgS": 4.517760148038581,
          "cElapsedS": 3781209,
          "vmgR": 6.230140755585879,
          "tcf": "1.000",
          "cElapsedR": 3648651,
          "dtf": 605234,
          "ceElapsedSFormatted": "43d 18h 20m 9s",
          "id": 20,
          "dmg": 4481049,
          "status": "RACING"
        },
        {
          "eElapsedR": 4138795,
          "eElapsedS": 3993071,
          "old": false,
          "eElapsedRFormatted": "47d 21h 39m 55s",
          "d24": 97321,
          "started": true,
          "finished": false,
          "eFinishS": 1769703311,
          "eFinishR": 1769849035,
          "ceElapsedRFormatted": "47d 21h 39m 55s",
          "eElapsedSFormatted": "46d 5h 11m 11s",
          "rankR": 4,
          "rankS": 4,
          "vmgS": 4.278059158021288,
          "cElapsedS": 3993071,
          "vmgR": 3.533975017608192,
          "tcf": "1.000",
          "cElapsedR": 4138795,
          "dtf": 822464,
          "ceElapsedSFormatted": "46d 5h 11m 11s",
          "id": 3,
          "dmg": 4092705,
          "status": "RACING"
        },
        {
          "eElapsedR": 4638893,
          "eElapsedS": 5414507,
          "old": false,
          "eElapsedRFormatted": "53d 16h 34m 53s",
          "d24": 125763,
          "started": true,
          "finished": false,
          "eFinishS": 1771127507,
          "eFinishR": 1770351893,
          "ceElapsedRFormatted": "53d 16h 34m 53s",
          "eElapsedSFormatted": "62d 16h 1m 47s",
          "rankR": 5,
          "rankS": 5,
          "vmgS": 3.1549676679345415,
          "cElapsedS": 5414507,
          "vmgR": 4.980177652878837,
          "tcf": "1.000",
          "cElapsedR": 4638893,
          "dtf": 1854685,
          "ceElapsedSFormatted": "62d 16h 1m 47s",
          "id": 26,
          "dmg": 3278911,
          "status": "RACING"
        }
      ],
      "id": 78459,
      "type": "LEVEL"
    },
    {
      "teams": [
        {
          "cElapsed": 2707680,
          "old": false,
          "d24": 128771,
          "started": true,
          "finished": true,
          "elapsed": 2707680,
          "cElapsedFormatted": "31d 8h 8m 0s",
          "rankR": 1,
          "rankS": 1,
          "tcf": "1.000",
          "dtf": 0,
          "id": 14,
          "finishAt": 1768419240,
          "elapsedFormatted": "31d 8h 8m 0s",
          "dmg": 4961713,
          "status": "RACING"
        },
        {
          "cElapsed": 2802060,
          "old": false,
          "d24": 154195,
          "started": true,
          "finished": true,
          "elapsed": 2802060,
          "cElapsedFormatted": "32d 10h 21m 0s",
          "rankR": 2,
          "rankS": 2,
          "tcf": "1.000",
          "dtf": 0,
          "id": 16,
          "finishAt": 1768513860,
          "elapsedFormatted": "32d 10h 21m 0s",
          "dmg": 4970999,
          "status": "RACING"
        },
        {
          "cElapsed": 2945460,
          "old": false,
          "d24": 131402,
          "started": true,
          "finished": true,
          "elapsed": 2945460,
          "cElapsedFormatted": "34d 2h 11m 0s",
          "rankR": 3,
          "rankS": 3,
          "tcf": "1.000",
          "dtf": 0,
          "id": 15,
          "finishAt": 1768657140,
          "elapsedFormatted": "34d 2h 11m 0s",
          "dmg": 4966715,
          "status": "RACING"
        },
        {
          "cElapsed": 3033900,
          "old": false,
          "d24": 107116,
          "started": true,
          "finished": true,
          "elapsed": 3033900,
          "cElapsedFormatted": "35d 2h 45m 0s",
          "rankR": 4,
          "rankS": 4,
          "tcf": "1.000",
          "dtf": 0,
          "id": 2,
          "finishAt": 1768744020,
          "elapsedFormatted": "35d 2h 45m 0s",
          "dmg": 4933692,
          "status": "RACING"
        },
        {
          "cElapsed": 3065400,
          "old": false,
          "d24": 168055,
          "started": true,
          "finished": true,
          "elapsed": 3065400,
          "cElapsedFormatted": "35d 11h 30m 0s",
          "rankR": 5,
          "rankS": 5,
          "tcf": "1.000",
          "dtf": 0,
          "id": 19,
          "finishAt": 1768777560,
          "elapsedFormatted": "35d 11h 30m 0s",
          "dmg": 5003931,
          "status": "RACING"
        },
        {
          "cElapsed": 3153480,
          "old": false,
          "d24": 157514,
          "started": true,
          "finished": true,
          "elapsed": 3153480,
          "cElapsedFormatted": "36d 11h 58m 0s",
          "rankR": 6,
          "rankS": 6,
          "tcf": "1.000",
          "dtf": 0,
          "id": 27,
          "finishAt": 1768866600,
          "elapsedFormatted": "36d 11h 58m 0s",
          "dmg": 4984428,
          "status": "RACING"
        },
        {
          "cElapsed": 3193380,
          "old": false,
          "d24": 148902,
          "started": true,
          "finished": true,
          "elapsed": 3193380,
          "cElapsedFormatted": "36d 23h 3m 0s",
          "rankR": 7,
          "rankS": 7,
          "tcf": "1.000",
          "dtf": 0,
          "id": 13,
          "finishAt": 1768904820,
          "elapsedFormatted": "36d 23h 3m 0s",
          "dmg": 4975343,
          "status": "RACING"
        },
        {
          "cElapsed": 3201180,
          "old": false,
          "d24": 140941,
          "started": true,
          "finished": true,
          "elapsed": 3201180,
          "cElapsedFormatted": "37d 1h 13m 0s",
          "rankR": 8,
          "rankS": 8,
          "tcf": "1.000",
          "dtf": 0,
          "id": 23,
          "finishAt": 1768913820,
          "elapsedFormatted": "37d 1h 13m 0s",
          "dmg": 4890226,
          "status": "RACING"
        },
        {
          "cElapsed": 3297600,
          "old": false,
          "d24": 152344,
          "started": true,
          "finished": true,
          "elapsed": 3297600,
          "cElapsedFormatted": "38d 4h 0m 0s",
          "rankR": 9,
          "rankS": 9,
          "tcf": "1.000",
          "dtf": 0,
          "id": 7,
          "finishAt": 1769008320,
          "elapsedFormatted": "38d 4h 0m 0s",
          "dmg": 4987043,
          "status": "RACING"
        },
        {
          "eElapsedR": 3316860,
          "eElapsedS": 3317362,
          "old": false,
          "eElapsedRFormatted": "38d 9h 21m 0s",
          "d24": 142693,
          "started": true,
          "finished": false,
          "eFinishS": 1769028442,
          "eFinishR": 1769027940,
          "ceElapsedRFormatted": "38d 9h 21m 0s",
          "eElapsedSFormatted": "38d 9h 29m 22s",
          "rankR": 10,
          "rankS": 10,
          "vmgS": 5.149450767100888,
          "cElapsedS": 3317362,
          "vmgR": 5.948656187188626,
          "tcf": "1.000",
          "cElapsedR": 3316860,
          "dtf": 5353,
          "ceElapsedSFormatted": "38d 9h 29m 22s",
          "id": 10,
          "dmg": 4983163,
          "status": "RACING"
        },
        {
          "eElapsedR": 3362153,
          "eElapsedS": 3372818,
          "old": false,
          "eElapsedRFormatted": "38d 21h 55m 53s",
          "d24": 140011,
          "started": true,
          "finished": false,
          "eFinishS": 1769084738,
          "eFinishR": 1769074073,
          "ceElapsedRFormatted": "38d 21h 55m 53s",
          "eElapsedSFormatted": "39d 0h 53m 38s",
          "rankR": 11,
          "rankS": 11,
          "vmgS": 5.064783813655568,
          "cElapsedS": 3372818,
          "vmgR": 6.102153211971003,
          "tcf": "1.000",
          "cElapsedR": 3362153,
          "dtf": 88264,
          "ceElapsedSFormatted": "39d 0h 53m 38s",
          "id": 17,
          "dmg": 4916730,
          "status": "RACING"
        },
        {
          "eElapsedR": 3414797,
          "eElapsedS": 3447793,
          "old": false,
          "eElapsedRFormatted": "39d 12h 33m 17s",
          "d24": 144177,
          "started": true,
          "finished": false,
          "eFinishS": 1769161633,
          "eFinishR": 1769128637,
          "ceElapsedRFormatted": "39d 12h 33m 17s",
          "eElapsedSFormatted": "39d 21h 43m 13s",
          "rankR": 12,
          "rankS": 12,
          "vmgS": 4.954646365753952,
          "cElapsedS": 3447793,
          "vmgR": 6.437748252972931,
          "tcf": "1.000",
          "cElapsedR": 3414797,
          "dtf": 197123,
          "ceElapsedSFormatted": "39d 21h 43m 13s",
          "id": 33,
          "dmg": 4757377,
          "status": "RACING"
        },
        {
          "eElapsedR": 3451296,
          "eElapsedS": 3483117,
          "old": false,
          "eElapsedRFormatted": "39d 22h 41m 36s",
          "d24": 132433,
          "started": true,
          "finished": false,
          "eFinishS": 1769197077,
          "eFinishR": 1769165256,
          "ceElapsedRFormatted": "39d 22h 41m 36s",
          "eElapsedSFormatted": "40d 7h 31m 57s",
          "rankR": 13,
          "rankS": 13,
          "vmgS": 4.904398613434057,
          "cElapsedS": 3483117,
          "vmgR": 5.967149759177435,
          "tcf": "1.000",
          "cElapsedR": 3451296,
          "dtf": 243410,
          "ceElapsedSFormatted": "40d 7h 31m 57s",
          "id": 34,
          "dmg": 4706738,
          "status": "RACING"
        },
        {
          "eElapsedR": 3442813,
          "eElapsedS": 3489919,
          "old": false,
          "eElapsedRFormatted": "39d 20h 20m 13s",
          "d24": 138927,
          "started": true,
          "finished": false,
          "eFinishS": 1769200399,
          "eFinishR": 1769153293,
          "ceElapsedRFormatted": "39d 20h 20m 13s",
          "eElapsedSFormatted": "40d 9h 25m 19s",
          "rankR": 14,
          "rankS": 14,
          "vmgS": 4.894840473735954,
          "cElapsedS": 3489919,
          "vmgR": 6.6041586622066575,
          "tcf": "1.000",
          "cElapsedR": 3442813,
          "dtf": 247460,
          "ceElapsedSFormatted": "40d 9h 25m 19s",
          "id": 5,
          "dmg": 4776675,
          "status": "RACING"
        },
        {
          "eElapsedR": 3506635,
          "eElapsedS": 3598089,
          "old": false,
          "eElapsedRFormatted": "40d 14h 3m 55s",
          "d24": 160142,
          "started": true,
          "finished": false,
          "eFinishS": 1769312769,
          "eFinishR": 1769221315,
          "ceElapsedRFormatted": "40d 14h 3m 55s",
          "eElapsedSFormatted": "41d 15h 28m 9s",
          "rankR": 15,
          "rankS": 15,
          "vmgS": 4.747685295103189,
          "cElapsedS": 3598089,
          "vmgR": 6.814209847289504,
          "tcf": "1.000",
          "cElapsedR": 3506635,
          "dtf": 397703,
          "ceElapsedSFormatted": "41d 15h 28m 9s",
          "id": 40,
          "dmg": 4558855,
          "status": "RACING"
        },
        {
          "eElapsedR": 3610724,
          "eElapsedS": 3717665,
          "old": false,
          "eElapsedRFormatted": "41d 18h 58m 44s",
          "d24": 143682,
          "started": true,
          "finished": false,
          "eFinishS": 1769431385,
          "eFinishR": 1769324444,
          "ceElapsedRFormatted": "41d 18h 58m 44s",
          "eElapsedSFormatted": "43d 0h 41m 5s",
          "rankR": 16,
          "rankS": 16,
          "vmgS": 4.59497961354953,
          "cElapsedS": 3717665,
          "vmgR": 6.163729589426269,
          "tcf": "1.000",
          "cElapsedR": 3610724,
          "dtf": 536311,
          "ceElapsedSFormatted": "43d 0h 41m 5s",
          "id": 32,
          "dmg": 4387043,
          "status": "RACING"
        },
        {
          "eElapsedR": 3674435,
          "eElapsedS": 3780013,
          "old": false,
          "eElapsedRFormatted": "42d 12h 40m 35s",
          "d24": 141285,
          "started": true,
          "finished": false,
          "eFinishS": 1769493253,
          "eFinishR": 1769387675,
          "ceElapsedRFormatted": "42d 12h 40m 35s",
          "eElapsedSFormatted": "43d 18h 0m 13s",
          "rankR": 17,
          "rankS": 17,
          "vmgS": 4.519189013600028,
          "cElapsedS": 3780013,
          "vmgR": 5.786640141411118,
          "tcf": "1.000",
          "cElapsedR": 3674435,
          "dtf": 605099,
          "ceElapsedSFormatted": "43d 18h 0m 13s",
          "id": 28,
          "dmg": 4390195,
          "status": "RACING"
        },
        {
          "eElapsedR": 3651117,
          "eElapsedS": 3781094,
          "old": false,
          "eElapsedRFormatted": "42d 6h 11m 57s",
          "d24": 146340,
          "started": true,
          "finished": false,
          "eFinishS": 1769495534,
          "eFinishR": 1769365557,
          "ceElapsedRFormatted": "42d 6h 11m 57s",
          "eElapsedSFormatted": "43d 18h 18m 14s",
          "rankR": 18,
          "rankS": 18,
          "vmgS": 4.517897032286437,
          "cElapsedS": 3781094,
          "vmgR": 6.1750718134451095,
          "tcf": "1.000",
          "cElapsedR": 3651117,
          "dtf": 607820,
          "ceElapsedSFormatted": "43d 18h 18m 14s",
          "id": 38,
          "dmg": 4336698,
          "status": "RACING"
        },
        {
          "eElapsedR": 3637102,
          "eElapsedS": 3807439,
          "old": false,
          "eElapsedRFormatted": "42d 2h 18m 22s",
          "d24": 158411,
          "started": true,
          "finished": false,
          "eFinishS": 1769522479,
          "eFinishR": 1769352142,
          "ceElapsedRFormatted": "42d 2h 18m 22s",
          "eElapsedSFormatted": "44d 1h 37m 19s",
          "rankR": 19,
          "rankS": 19,
          "vmgS": 4.486635960121709,
          "cElapsedS": 3807439,
          "vmgR": 6.728233220476782,
          "tcf": "1.000",
          "cElapsedR": 3637102,
          "dtf": 637195,
          "ceElapsedSFormatted": "44d 1h 37m 19s",
          "id": 43,
          "dmg": 4512241,
          "status": "RACING"
        },
        {
          "eElapsedR": 3720958,
          "eElapsedS": 3833434,
          "old": false,
          "eElapsedRFormatted": "43d 1h 35m 58s",
          "d24": 134500,
          "started": true,
          "finished": false,
          "eFinishS": 1769545474,
          "eFinishR": 1769432998,
          "ceElapsedRFormatted": "43d 1h 35m 58s",
          "eElapsedSFormatted": "44d 8h 50m 34s",
          "rankR": 20,
          "rankS": 20,
          "vmgS": 4.456211800757062,
          "cElapsedS": 3833434,
          "vmgR": 5.64452079540085,
          "tcf": "1.000",
          "cElapsedR": 3720958,
          "dtf": 661337,
          "ceElapsedSFormatted": "44d 8h 50m 34s",
          "id": 18,
          "dmg": 4463738,
          "status": "RACING"
        },
        {
          "eElapsedR": 3737277,
          "eElapsedS": 3900838,
          "old": false,
          "eElapsedRFormatted": "43d 6h 7m 57s",
          "d24": 143738,
          "started": true,
          "finished": false,
          "eFinishS": 1769614318,
          "eFinishR": 1769450757,
          "ceElapsedRFormatted": "43d 6h 7m 57s",
          "eElapsedSFormatted": "45d 3h 33m 58s",
          "rankR": 21,
          "rankS": 21,
          "vmgS": 4.379211745141887,
          "cElapsedS": 3900838,
          "vmgR": 6.008749249667588,
          "tcf": "1.000",
          "cElapsedR": 3737277,
          "dtf": 733655,
          "ceElapsedSFormatted": "45d 3h 33m 58s",
          "id": 30,
          "dmg": 4267427,
          "status": "RACING"
        },
        {
          "eElapsedR": 3790234,
          "eElapsedS": 3953131,
          "old": false,
          "eElapsedRFormatted": "43d 20h 50m 34s",
          "d24": 137987,
          "started": true,
          "finished": false,
          "eFinishS": 1769664331,
          "eFinishR": 1769501434,
          "ceElapsedRFormatted": "43d 20h 50m 34s",
          "eElapsedSFormatted": "45d 18h 5m 31s",
          "rankR": 22,
          "rankS": 22,
          "vmgS": 4.321282731656091,
          "cElapsedS": 3953131,
          "vmgR": 5.757193648032995,
          "tcf": "1.000",
          "cElapsedR": 3790234,
          "dtf": 783982,
          "ceElapsedSFormatted": "45d 18h 5m 31s",
          "id": 11,
          "dmg": 4255140,
          "status": "RACING"
        },
        {
          "eElapsedR": 3974483,
          "eElapsedS": 4052858,
          "old": false,
          "eElapsedRFormatted": "46d 0h 1m 23s",
          "d24": 116397,
          "started": true,
          "finished": false,
          "eFinishS": 1769765618,
          "eFinishR": 1769687243,
          "ceElapsedRFormatted": "46d 0h 1m 23s",
          "eElapsedSFormatted": "46d 21h 47m 38s",
          "rankR": 23,
          "rankS": 23,
          "vmgS": 4.214950367275307,
          "cElapsedS": 4052858,
          "vmgR": 4.7036013424769685,
          "tcf": "1.000",
          "cElapsedR": 3974483,
          "dtf": 883281,
          "ceElapsedSFormatted": "46d 21h 47m 38s",
          "id": 24,
          "dmg": 4144897,
          "status": "RACING"
        },
        {
          "eElapsedR": 3824664,
          "eElapsedS": 4063431,
          "old": false,
          "eElapsedRFormatted": "44d 6h 24m 24s",
          "d24": 149934,
          "started": true,
          "finished": false,
          "eFinishS": 1769774391,
          "eFinishR": 1769535624,
          "ceElapsedRFormatted": "44d 6h 24m 24s",
          "eElapsedSFormatted": "47d 0h 43m 51s",
          "rankR": 24,
          "rankS": 24,
          "vmgS": 4.203983168976963,
          "cElapsedS": 4063431,
          "vmgR": 6.118045718700773,
          "tcf": "1.000",
          "cElapsedR": 3824664,
          "dtf": 891228,
          "ceElapsedSFormatted": "47d 0h 43m 51s",
          "id": 9,
          "dmg": 4188165,
          "status": "RACING"
        },
        {
          "eElapsedR": 4014069,
          "eElapsedS": 4102859,
          "old": false,
          "eElapsedRFormatted": "46d 11h 1m 9s",
          "d24": 111838,
          "started": true,
          "finished": false,
          "eFinishS": 1769816219,
          "eFinishR": 1769727429,
          "ceElapsedRFormatted": "46d 11h 1m 9s",
          "eElapsedSFormatted": "47d 11h 40m 59s",
          "rankR": 25,
          "rankS": 25,
          "vmgS": 4.163582738269205,
          "cElapsedS": 4102859,
          "vmgR": 4.6797424741563995,
          "tcf": "1.000",
          "cElapsedR": 4014069,
          "dtf": 931037,
          "ceElapsedSFormatted": "47d 11h 40m 59s",
          "id": 29,
          "dmg": 4058778,
          "status": "RACING"
        },
        {
          "eElapsedR": 3995666,
          "eElapsedS": 4178350,
          "old": false,
          "eElapsedRFormatted": "46d 5h 54m 26s",
          "d24": 121706,
          "started": true,
          "finished": false,
          "eFinishS": 1769892430,
          "eFinishR": 1769709746,
          "ceElapsedRFormatted": "46d 5h 54m 26s",
          "eElapsedSFormatted": "48d 8h 39m 10s",
          "rankR": 26,
          "rankS": 26,
          "vmgS": 4.088358756113975,
          "cElapsedS": 4178350,
          "vmgR": 5.157604363824301,
          "tcf": "1.000",
          "cElapsedR": 3995666,
          "dtf": 1000733,
          "ceElapsedSFormatted": "48d 8h 39m 10s",
          "id": 35,
          "dmg": 3975340,
          "status": "RACING"
        },
        {
          "eElapsedR": 4320744,
          "eElapsedS": 4641490,
          "old": false,
          "eElapsedRFormatted": "50d 0h 12m 24s",
          "d24": 121399,
          "started": true,
          "finished": false,
          "eFinishS": 1770356290,
          "eFinishR": 1770035544,
          "ceElapsedRFormatted": "50d 0h 12m 24s",
          "eElapsedSFormatted": "53d 17h 18m 10s",
          "rankR": 27,
          "rankS": 27,
          "vmgS": 3.6804118477750274,
          "cElapsedS": 4641490,
          "vmgR": 4.832843035890032,
          "tcf": "1.000",
          "cElapsedR": 4320744,
          "dtf": 1375129,
          "ceElapsedSFormatted": "53d 17h 18m 10s",
          "id": 41,
          "dmg": 3727073,
          "status": "RACING"
        },
        {
          "eElapsedR": 4502416,
          "eElapsedS": 5126289,
          "old": false,
          "eElapsedRFormatted": "52d 2h 40m 16s",
          "d24": 122879,
          "started": true,
          "finished": false,
          "eFinishS": 1770840849,
          "eFinishR": 1770216976,
          "ceElapsedRFormatted": "52d 2h 40m 16s",
          "eElapsedSFormatted": "59d 7h 58m 9s",
          "rankR": 28,
          "rankS": 28,
          "vmgS": 3.3323514965830063,
          "cElapsedS": 5126289,
          "vmgR": 5.056529319039967,
          "tcf": "1.000",
          "cElapsedR": 4502416,
          "dtf": 1693615,
          "ceElapsedSFormatted": "59d 7h 58m 9s",
          "id": 39,
          "dmg": 3377164,
          "status": "RACING"
        },
        {
          "eElapsedR": 4900622,
          "eElapsedS": 5154400,
          "old": true,
          "eElapsedRFormatted": "56d 17h 17m 2s",
          "d24": 78739,
          "started": true,
          "finished": false,
          "eFinishS": 1770868600,
          "eFinishR": 1770614822,
          "ceElapsedRFormatted": "56d 17h 17m 2s",
          "eElapsedSFormatted": "59d 15h 46m 40s",
          "rankR": 29,
          "rankS": 29,
          "vmgS": 3.314177184989787,
          "cElapsedS": 5154400,
          "vmgR": 3.820476464517798,
          "tcf": "1.000",
          "cElapsedR": 4900622,
          "dtf": 1762937,
          "ceElapsedSFormatted": "59d 15h 46m 40s",
          "id": 36,
          "dmg": 4737279,
          "status": "RACING"
        }
      ],
      "id": 78460,
      "type": "LEVEL"
    }
  ]
}